{
    "player": [
      {
        "name": "BATSMEN",
        "imageId": 174146
      },
      {
        "id": "624",
        "name": "Eoin Morgan",
        "imageId": 170936,
        "battingStyle": "Left-hand bat",
        "bowlingStyle": "Right-arm medium"
      },
      {
        "id": "8019",
        "name": "Joe Root",
        "imageId": 170942,
        "battingStyle": "Right-hand bat",
        "bowlingStyle": "Right-arm offbreak"
      },
      {
        "id": "6534",
        "name": "Jason Roy",
        "imageId": 170941,
        "battingStyle": "Right-hand bat"
      },
      {
        "id": "10045",
        "name": "Liam Livingstone",
        "imageId": 244797,
        "battingStyle": "Right-hand bat",
        "bowlingStyle": "Right-arm legbreak"
      },
      {
        "id": "6660",
        "name": "Dawid Malan",
        "imageId": 244793,
        "battingStyle": "Left-hand bat",
        "bowlingStyle": "Right-arm legbreak"
      },
      {
        "name": "ALL ROUNDER",
        "imageId": 174146
      },
      {
        "id": "6692",
        "name": "Moeen Ali",
        "imageId": 244796,
        "battingStyle": "Left-hand bat",
        "bowlingStyle": "Right-arm offbreak"
      },
      {
        "id": "6557",
        "name": "Ben Stokes",
        "imageId": 244791,
        "battingStyle": "Left-hand bat",
        "bowlingStyle": "Right-arm fast-medium"
      },
      {
        "id": "6670",
        "name": "Chris Woakes",
        "imageId": 244787,
        "battingStyle": "Right-hand bat",
        "bowlingStyle": "Right-arm fast-medium"
      },
      {
        "id": "9522",
        "name": "Tom Curran",
        "imageId": 170967,
        "battingStyle": "Right-hand bat",
        "bowlingStyle": "Right-arm fast-medium"
      },
      {
        "id": "7854",
        "name": "Lewis Gregory",
        "imageId": 180929,
        "battingStyle": "Right-hand bat",
        "bowlingStyle": "Right-arm fast-medium"
      },
      {
        "id": "10420",
        "name": "Sam Curran",
        "imageId": 244812,
        "battingStyle": "Left-hand bat",
        "bowlingStyle": "Left-arm fast-medium"
      },
      {
        "name": "WICKET KEEPER",
        "imageId": 174146
      },
      {
        "id": "6507",
        "name": "Jonny Bairstow",
        "imageId": 170976,
        "battingStyle": "Right-hand bat",
        "bowlingStyle": "Right-arm medium"
      },
      {
        "id": "2258",
        "name": "Jos Buttler",
        "imageId": 244800,
        "battingStyle": "Right-hand bat"
      },
      {
        "id": "7990",
        "name": "Sam Billings",
        "imageId": 156173,
        "battingStyle": "Right-hand bat"
      },
      {
        "name": "BOWLER",
        "imageId": 174146
      },
      {
        "id": "1742",
        "name": "Adil Rashid",
        "imageId": 244789,
        "battingStyle": "Right-hand bat",
        "bowlingStyle": "Right-arm legbreak"
      },
      {
        "id": "8383",
        "name": "Mark Wood",
        "imageId": 244802,
        "battingStyle": "Right-hand bat",
        "bowlingStyle": "Right-arm fast"
      },
      {
        "id": "11540",
        "name": "Jofra Archer",
        "imageId": 170970,
        "battingStyle": "Right-hand bat",
        "bowlingStyle": "Right-arm fast"
      },
      {
        "id": "8022",
        "name": "Olly Stone",
        "imageId": 156823,
        "battingStyle": "Right-hand bat",
        "bowlingStyle": "Right-arm fast"
      },
      {
        "id": "8349",
        "name": "Reece Topley",
        "imageId": 244807,
        "battingStyle": "Right-hand bat",
        "bowlingStyle": "Left-arm fast-medium"
      },
      {
        "id": "6532",
        "name": "Chris Jordan",
        "imageId": 244783,
        "battingStyle": "Right-hand bat",
        "bowlingStyle": "Right-arm fast-medium"
      }
    ]
  }